Metadata-Version: 2.1
Name: batukh
Version: 0.1.1.1
Summary: Document recognizer for multiple languages.
Home-page: https://github.com/KoshurNizam/batukh
Author: Murtaza, Wajid, Naveed
Author-email: batukhorg@gmail.com
License: UNKNOWN
Platform: UNKNOWN
Classifier: Programming Language :: Python :: 3
Classifier: License :: OSI Approved :: GNU General Public License v3 (GPLv3)
Classifier: Operating System :: OS Independent
Requires-Python: >=3.6
Requires-Dist: numpy
Requires-Dist: tensorboard
Requires-Dist: tqdm
Provides-Extra: full
Requires-Dist: tensorflow ; extra == 'full'
Requires-Dist: tensorflow-addons ; extra == 'full'
Requires-Dist: torch ; extra == 'full'
Requires-Dist: torchvision ; extra == 'full'
Requires-Dist: Pillow ; extra == 'full'
Provides-Extra: tf
Requires-Dist: tensorflow ; extra == 'tf'
Requires-Dist: tensorflow-addons ; extra == 'tf'
Provides-Extra: torch
Requires-Dist: torch ; extra == 'torch'
Requires-Dist: torchvision ; extra == 'torch'
Requires-Dist: Pillow ; extra == 'torch'
